<?xml version="1.0" encoding="UTF-8" ?>
<Report name="Project Report" reportType="RP_PROGRESS" pdfType="RPTP_PROGRESS" pdfFiles="ProjectReportPDF" personId="0" ajax="true" disabled="false">
    <Permissions>
        <Role role="HQP">
            <SectionPermission id="instructions" permissions="rw" />
            <SectionPermission id="information" permissions="r" />
            <SectionPermission id="summary" permissions="-" />
            <SectionPermission id="figures" permissions="-" />
            <SectionPermission id="milestones" permissions="" />
            <SectionPermission id="achievements" permissions="-" />
            <SectionPermission id="hqp" permissions="rw" />
            <SectionPermission id="networking" permissions="-" />
            <SectionPermission id="ktee" permissions="r" />
            <SectionPermission id="budget" permissions="-" />
            <SectionPermission id="contributions" permissions="-" />
            <SectionPermission id="ccv" permissions="-" />
            <SectionPermission id="extension" permissions="-" />
            <SectionPermission id="review" permissions="r" />
            <SectionPermission id="submit" permissions="-" />
        </Role>
        <Role role="FAKENI">
            <SectionPermission id="instructions" permissions="rw" />
            <SectionPermission id="information" permissions="rw" />
            <SectionPermission id="summary" permissions="" />
            <SectionPermission id="figures" permissions="rw" />
            <SectionPermission id="milestones" permissions="rw" />
            <SectionPermission id="achievements" permissions="rw" />
            <SectionPermission id="hqp" permissions="rw" />
            <SectionPermission id="networking" permissions="rw" />
            <SectionPermission id="ktee" permissions="rw" />
            <SectionPermission id="budget" permissions="rw" />
            <SectionPermission id="contributions" permissions="rw" />
            <SectionPermission id="ccv" permissions="rw" />
            <SectionPermission id="extension" permissions="-" />
            <SectionPermission id="review" permissions="r" />
            <SectionPermission id="submit" permissions="" />
        </Role>
        <Role role="CI">
            <SectionPermission id="instructions" permissions="rw" />
            <SectionPermission id="information" permissions="rw" />
            <SectionPermission id="summary" permissions="" />
            <SectionPermission id="milestones" permissions="rw" />
            <SectionPermission id="hqp" permissions="rw" />
            <SectionPermission id="networking" permissions="rw" />
            <SectionPermission id="ktee" permissions="rw" />
            <SectionPermission id="budget" permissions="rw" />
            <SectionPermission id="contributions" permissions="rw" />
            <SectionPermission id="ccv" permissions="rw" />
            <SectionPermission id="extension" permissions="-" />
            <SectionPermission id="review" permissions="r" />
            <SectionPermission id="submit" permissions="" />
        </Role>
        <Role role="AR">
            <SectionPermission id="instructions" permissions="rw" />
            <SectionPermission id="information" permissions="rw" />
            <SectionPermission id="summary" permissions="" />
            <SectionPermission id="milestones" permissions="rw" />
            <SectionPermission id="hqp" permissions="rw" />
            <SectionPermission id="networking" permissions="rw" />
            <SectionPermission id="ktee" permissions="rw" />
            <SectionPermission id="budget" permissions="rw" />
            <SectionPermission id="contributions" permissions="rw" />
            <SectionPermission id="ccv" permissions="rw" />
            <SectionPermission id="extension" permissions="-" />
            <SectionPermission id="review" permissions="r" />
            <SectionPermission id="submit" permissions="" />
        </Role>
        <Role role="PL">
            <SectionPermission id="instructions" permissions="rw" />
            <SectionPermission id="information" permissions="rw" />
            <SectionPermission id="summary" permissions="rw" />
            <SectionPermission id="milestones" permissions="rw" />
            <SectionPermission id="hqp" permissions="rw" />
            <SectionPermission id="networking" permissions="rw" />
            <SectionPermission id="ktee" permissions="rw" />
            <SectionPermission id="budget" permissions="rw" />
            <SectionPermission id="contributions" permissions="rw" />
            <SectionPermission id="ccv" permissions="rw" />
            <SectionPermission id="extension" permissions="-" />
            <SectionPermission id="review" permissions="rw" />
            <SectionPermission id="submit" permissions="rw" />
        </Role>
    </Permissions>
    <ReportSection id="instructions" type="ReportSection" name="Instructions">
        <If id="is_pl" if="{contains({$my_full_roles},PL)}">
            <!-- Project Leader View -->
            <![CDATA[
                <p><b>Deadline: May 10, 2024</b></p>
                <p><b>Before completing the report:</b></p>
                <ul>
                    <li>Update the personal information on your Forum profile</li>
                    <li>Update your products*, including publications, awards, presentations, patents, etc.; be sure to assign each one to a GlycoNet project, if applicable (see “Managing Products” on the <a target='_blank' href='http://canadianglycomics.ca/forum-help-and-faqs/'>Forum Help & FAQs</a> page)</li>
                    <li>Add any new members (trainees and collaborators) who are not already in the Forum (see “Managing People” on the <a target='_blank' href='http://canadianglycomics.ca/forum-help-and-faqs/'>Forum Help & FAQs</a> page)</li>
                    <li>Edit the roles and relations of any trainees that you supervise (see “Managing People” on the <a target='_blank' href='http://canadianglycomics.ca/forum-help-and-faqs/'>Forum Help & FAQs</a> page)</li>
                    <li>Add top research outcomes (found in the “Dashboard” tab on your project page)</li>
                </ul>
                <p><b>To complete your section of the report:</b></p>
                <ul>
                    <li>Fill in all applicable sections of the Project Report:
                        <ul>
                            <li>Project Information</li>
                            <li>Summary/Background</li>
                            <li>Figures</li>
                            <li>Milestones (all)</li>
                            <li>Achievements</li>
                            <li>KPI</li>
                            <!--li>Networking</li-->
                            <li>HQP</li>
                            <li>Budget</li>
                            <!--li>Partner Contributions</li-->
                            <!--li>CCV</li-->
                        </ul>
                    </li>
                    <li>Generate and preview project report PDF</li>
                    <li>Submit project report to GlycoNet Administrative Centre</li>
                </ul><br />
                <p>*Managing numerous publications can be challenging for investigators.  Therefore, <b>it is highly recommended that this task be delegated to trainees as much as possible.</b></p>
                <p><b>Need further assistance?</b></p>
                <p>Please visit the “Forum Help and FAQs” page on the GlycoNet website (<a href='http://canadianglycomics.ca/forum-help-and-faqs/' target='_blank'>http://canadianglycomics.ca/forum-help-and-faqs/</a>), or contact the GlycoNet Administrative Office (info@glyconet.ca).</p>
            ]]>
        </If>
        <If id="not_pl1" if="{and({or({contains({$my_full_roles},CI)},{contains({$my_full_roles},AR)},{contains({$my_full_roles},FAKENI)})},{!contains({$my_full_roles},PL)})}">
            <!-- Network Investigator View -->
            <![CDATA[
                <p><b>Deadline: April 15, 2023</b></p>
                <p><b>Before completing the report:</b></p>
                <ul>
                    <li>Update the personal information on your Forum profile</li>
                    <li>Update your products*, including publications, awards, presentations, patents, etc.; be sure to assign each one to a GlycoNet project, if applicable (see “Managing Products” on the <a target='_blank' href='http://canadianglycomics.ca/forum-help-and-faqs/'>Forum Help & FAQs</a> page)</li>
                    <li>Add any new members (trainees and collaborators) who are not already in the Forum (see “Managing People” on the <a target='_blank' href='http://canadianglycomics.ca/forum-help-and-faqs/'>Forum Help & FAQs</a> page)</li>
                    <li>Edit the roles and relations of any trainees that you supervise (see “Managing People” on the <a target='_blank' href='http://canadianglycomics.ca/forum-help-and-faqs/'>Forum Help & FAQs</a> page)</li>
                    <li>Add top research outcomes (found in the “Dashboard” tab on your profile page)</li>
                </ul>
                <p><b>To complete your section of the report:</b></p>
                <ul>
                    <li>Fill in all applicable sections of the Project Report:
                        <ul>
                            <li>Project Information</li>
                            <li>Figures</li>
                            <li>Milestones (assigned milestones only)</li>
                            <li>Achievements</li>
                            <li>KPI</li>
                            <!--li>Networking</li-->
                            <li>HQP</li>
                            <li>Budget</li>
                            <!--li>Partner Contributions</li-->
                            <!--li>CCV</li-->
                        </ul>
                    </li>
                </ul><br />
                <p>*Managing numerous publications can be challenging for investigators.  Therefore, <b>it is highly recommended that this task be delegated to trainees as much as possible.</b></p>
                <p><b>Need further assistance?</b></p>
                <p>Please visit the “Forum Help and FAQs” page on the GlycoNet website (<a href='http://canadianglycomics.ca/forum-help-and-faqs/' target='_blank'>http://canadianglycomics.ca/forum-help-and-faqs/</a>), or contact the GlycoNet Administrative Office (info@glyconet.ca).</p>
            ]]>
        </If>
        <If id="not_pl2" if="{and({contains({$my_full_roles},HQP)},{!contains({$my_full_roles},PL)})}">
            <!-- HQP View -->
            <ReportItem id="roles" type="TextareaReportItem" blobItem="ROLES" blobSubItem="{$my_id}">
                <![CDATA[
                    <p><b>Deadline: March 17, 2021</b></p>
                    <p><b>Before completing the report:</b></p>
                    <ul>
                        <li>Update the personal information on your Forum profile, including gender, nationality, and alumni status if you will be leaving the Network in the near future (see “Getting Started with the GlycoNet Forum” on the <a target='_blank' href='http://canadianglycomics.ca/forum-help-and-faqs/'>Forum Help & FAQs</a> page)</li>
                        <li>Update your products, including publications, awards, presentations, patents, etc.; be sure to assign each one to a GlycoNet project, if applicable (see “Managing Products” on the <a target='_blank' href='http://canadianglycomics.ca/forum-help-and-faqs/'>Forum Help & FAQs</a> page)</li>
                    </ul>
                    <p><b>To complete your section of the report:</b></p>
                    <ul>
                        <li>Fill in the HQP section in the Project Report</li>
                    </ul>
                    <p><b>Need further assistance?</b></p>
                    <p>Please visit the “Forum Help and FAQs” page on the GlycoNet website (<a href='http://canadianglycomics.ca/forum-help-and-faqs/' target='_blank'>http://canadianglycomics.ca/forum-help-and-faqs/</a>), or contact the GlycoNet Administrative Office (info@glyconet.ca).</p>
                ]]>
            </ReportItem>
        </If>
    </ReportSection>
    <ReportSection id="information" type="EditableReportSection" name="Project Information" blobSection="INFORMATION">
        <Static>
            <![CDATA[
                <p><b>Research Area:</b>  {$project_theme}</p>
                <p><b>Project Title:</b>  {$project_name} - {$project_full_name}</p>
                <p><b>Project Leader:</b> {$project_leaders}<br />
            ]]>
        </Static>
        <ReportItemSet id="leaders" type="ProjectLeaders">
            <ReportItem id="leader_info">
                <![CDATA[
                    Location:       {$user_name}<br />
                    E-mail address: {$user_email}<br />
                ]]>
            </ReportItem>
        </ReportItemSet>
        <Static>
            <![CDATA[
                </p>
                <p><b>Investigators:</b><br />
                    Add % Time Devoted to Project for each investigator (Please note that only funded investigators will be shown in this section).
                </p>
                <table class='wikitable'>
                    <tr>
                        <th>Name</th>
                        <th>Location</th>
                        <th>E-mail address</th>
                        <th>% Time Devoted<br />to Project</th>
                    </tr>
            ]]>
        </Static>
        <ReportItemSet id="co-investigators" type="ProjectPeople" role="PL,NFI,NI" startDate="{$this_year}-04-01 00:00:00" endDate="{$next_year}-04-30 00:00:00">
            <ReportItem id="investigators_info" type="IntegerReportItem" min="0" max="100" size="3" blobItem="TIME" blobSubItem="{$user_id}">
                <![CDATA[
                    <tr>
                        <td>{$user_name}</td>
                        <td>{$user_uni}</td>
                        <td>{$user_email}</td>
                        <td align="center">{$item}</td>
                    </tr>
                ]]>
            </ReportItem>
        </ReportItemSet>
        <Static>
            <![CDATA[
                </table>
            ]]>
        </Static>
        <ReportItem id="partners_table" type="MultiText" blobType="BLOB_ARRAY" blobItem="PARTNERS" labels="Company/Organization Name|Cash|In-kind|Contact Full Name|Email|Other Details" sizes="|100|100|||" types="Text|Text|Text|Text|Text|Textarea" multiple="true" addText="Add Partner">
            <![CDATA[
                <p><b>Partners:</b><br />
                    List all <b>Partners Involved</b> (those providing matching): company/organization name, committed cash/in-kind contributions, contact full name, email, other details.
                </p>
                {$item}
            ]]>
        </ReportItem>
        <ReportItem id="collaborators_table" type="MultiText" blobType="BLOB_ARRAY" blobItem="COLLABORATORS" labels="Full Name|Email|Institution/Organization/Company|Department (if applicable)|Role in the Project" sizes="||200||" multiple="true" addText="Add Collaborator">
            <![CDATA[
                <p><b>Collaborators:</b><br />
                    List all Collaborators Involved (not funded)</b>
                </p>
                {$item}
            ]]>
        </ReportItem>
    </ReportSection>
    <ReportSection id="summary" type="EditableReportSection" name="Report" blobSection="REPORT">
        <ReportItem id="report" type="UploadReportItem" blobItem="REPORT" fileSize="10" mimeType="application/pdf">
            <![CDATA[
                <p>Please ensure that all sections and questions in this report template are fully answered. If a particular section does not apply to your project, please indicate this by writing 'Not Applicable' or 'N/A' <b>and provide a brief explanation as to why</b>. Incomplete responses without adequate explanation may impact the assessment of your project’s progress.</p>
                
                <p>Please note that this information will be provided to the GlycoNet Research Management Committee and Scientific Advisory Board for evaluation of performance. Your thorough and accurate reporting is important for maintaining transparency and ensuring continued support from GlycoNet.</p>
                <p>Download the <a href="{$wgServer}{$wgScriptPath}/data/GlycoNet Annual Report - Narrative Template.docx" target="_blank"><b>Report Template</b></a>, and then upload a <b>PDF</b> below.</p>
                {$item}
            ]]>
        </ReportItem>
    </ReportSection>
    <ReportSection id="milestones" type="EditableReportSection" blobSection="MILESTONES" name="Milestones" title="Milestones">
        <ReportItem id="table" type="ProjectMilestoneTable">
            <![CDATA[
                {$item}<br />
                <a href='{$project_url}?tab=milestones&edit' class='button' target='_blank'>Edit Milestones</a><br />
                <small>(Opens in a new Tab)</small>
                <br /><br /><br /><br /><br /><br /><br /><br />
            ]]>
        </ReportItem>
        <ReportItemSet type="ToggleHeaderReportItemSet" title="Last Year's Milestones">
            <ReportItem id="table" type="ProjectMilestoneTable" date="{$this_year}-04-01 00:00:00">
                <![CDATA[
                    {$item}
                    <br /><br /><br /><br /><br /><br /><br /><br /><br />
                ]]>
            </ReportItem>
        </ReportItemSet>
        <ReportItem id="comments" type="TextareaReportItem" blobItem="COMMENTS">
            <![CDATA[
                <h3>Comments</h3>
                <p>If any of the milestones have been delayed or abandoned, please comment on them below.<br />
                    <b>Please Note:</b> If a new milestone is to be added, please provide a justification.
                </p>
                {$item}
            ]]>
        </ReportItem>
    </ReportSection>
    <ReportSection id="ktee" type="EditableReportSection" blobSection="KTEE" name="KPI" title="Key Performance Indicators">
        <ReportItem id="publications" type="ManageProductsReportItem">
            <![CDATA[
                <h2>Publications</h2>
                Please add all relevant publications, including the following:
                <ul>
                    <li><b>Peer-reviewed journal articles</b></li>
                    <li><b>Other refereed contributions</b> (e.g. papers in refereed conference proceedings, books)</li>
                    <li><b>Non-refereed contributions</b> (e.g. papers in non-refereed conference proceedings, letters)</li>
                    <li><b>Other specialized publications</b> (e.g. reports, briefings, online publications or other forms of grey literature)</li>
                </ul>
                
                <b>To add the publication:</b>
                <ol>
                    <li><b>Using DOI</b>: Click the <b>Add From DOI</b> button. This is the easiest way to import publication details. After the information has been exported, please verify its correctness.</li>
                    <li><b>Using CCV Upload</b>: You can also upload an updated CCV if it includes publications related to the project. Please ensure that you only report publications that are directly associated with the project.</li>
                    <li><b>Manually Adding Publications</b>: If necessary, click the <b>Add Product</b> button to manually enter publication details.</li>
                </ol>
                {$item}
            ]]>
        </ReportItem>
        <If if="{contains({$my_full_roles},PL)}">
            <!-- Project Leader View -->
            <ReportItem id="new" type="MultiText" blobItem="NEW" blobType="BLOB_ARRAY" labels="Type|Details" types="Select(Knowledge Product,Service,Process)|Textarea" sizes="|250" multiple="true">
                <![CDATA[
                    <h2>New or Improved Products (knowledge product, service, process)</h2>
                    {$item}
                ]]>
            </ReportItem>
            <ReportItem id="new_ip_filed" type="MultiText" blobItem="NEW_IP_FILED" blobType="BLOB_ARRAY" labels="Title|Type of IP|Filing and Application Number|Filing Date|Status of the Application" types="Text|Select(Patent,Trademark,Copyright,Another type of Protection)|Text|Date|Text" sizes="|||80|" multiple="true">
                <![CDATA[
                    <h2>Intellectual Properties</h2>
                    <h3>New IP filed</h3>
                    {$item}
                ]]>
            </ReportItem>
            <ReportItem id="new_ip_issued" type="MultiText" blobItem="NEW_IP_ISSUED" blobType="BLOB_ARRAY" labels="Title|Type of IP|Registration or Patent Number|Issue Date|Expiration Date" types="Text|Select(Patent,Trademark,Copyright,Another type of Protection)|Text|Date|Date" sizes="|||80|80" multiple="true">
                <![CDATA[
                    <h3>New IP Issued</h3>
                    {$item}
                ]]>
            </ReportItem>
            <ReportItem id="new_licenses_granted" type="MultiText" blobItem="NEW_LICENSES_GRANTED" blobType="BLOB_ARRAY" labels="Description of the Deal|Partners Involved|Date of Agreement|Revenue Impact|Strategic Relevance" types="Textarea|Textarea|Date|Textarea|Textarea" sizes="||80|||" multiple="true">
                <![CDATA[
                    <h3>New Licenses Granted</h3>
                    {$item}
                ]]>
            </ReportItem>
            <ReportItem id="new_licenses_negotiation" type="MultiText" blobItem="NEW_LICENSES_NEGOTIATION" blobType="BLOB_ARRAY" labels="Description of Potential Deal|Potential Partners Involved|Expected Date of Agreement|Projected Revenue Impact|Strategic Relevance" types="Textarea|Textarea|Date|Text|Textarea" sizes="||80|||" multiple="true">
                <![CDATA[
                    <h3>New Licenses Under Negotiation</h3>
                    {$item}
                ]]>
            </ReportItem>
            <ReportItem id="new_companies" type="MultiText" blobItem="NEW_COMPANIES" blobType="BLOB_ARRAY" labels="Company name|Date of Incorporation|Industry/Sector|Number of Employees|Initial Investment" types="Text|Date|Text|Text|Text" sizes="|80||||" multiple="true">
                <![CDATA[
                    <h2>Companies</h2>
                    <h3>New Companies Created</h3>
                    {$item}
                ]]>
            </ReportItem>
            <ReportItem id="enhanced_companies" type="MultiText" blobItem="ENHANCED_COMPANIES" blobType="BLOB_ARRAY" labels="Company name|Details about any new technologies adopted or developed|Upgrades or expansions in facilities that support growth|Revenue Growth|Other Details" types="Text|Textarea|Textarea|Text|Textarea" sizes="|200|200||200" multiple="true">
                <![CDATA[
                    <h3>Companies Enhanced</h3>
                    {$item}
                ]]>
            </ReportItem>
            <ReportItem id="forums" type="MultiText" blobItem="FORUMS" blobType="BLOB_ARRAY" labels="Forum Name|National or International|Event Date|Presentation Type|Other Details" types="Text|Select(National,International)|Date|ComboBox(Talk,Poster,Panel Discussion,Keynote Speech,Round Table)|Textarea" sizes="|125|80||" multiple="true">
                <![CDATA[
                    <h2>Instances where Knowledge is Presented</h2>
                    <h3>National and International Forums where knowledge is presented</h3>
                    {$item}
                ]]>
            </ReportItem>
            <ReportItem id="seminars" type="MultiText" blobItem="SEMINARS" blobType="BLOB_ARRAY" labels="Event Name|Seminar or Workshop|National or International|Event Date|Online, in-person or hybrid|Audience|Approximate number of attendants" types="Text|Select(Seminar,Workshop)|Select(National,International)|Date|Select(Online,In-Person,Hybrid)|Text|Text" sizes="|100|125|80|100||80" multiple="true">
                <![CDATA[
                    <h3>Seminars and Workshops</h3>
                    {$item}
                ]]>
            </ReportItem>
            <ReportItem id="jobs" type="MultiText" blobItem="JOBS" blobType="BLOB_ARRAY" labels="Company Name|Job/position|Date of position opened/started|Employee Full Name|Other Details" types="Text|Text|Date|Text|Textarea" sizes="||80||" multiple="true">
                <![CDATA[
                    <h2>Direct Jobs Created</h2>
                    <small>Refers to jobs/positions that did not exist prior to the project activities, and which were created as a result of the project activities. They do not include previously existing jobs/positions.</small>
                    {$item}
                ]]>
            </ReportItem>
        </If>
    </ReportSection>
    <ReportSection id="networking" type="EditableReportSection" blobSection="NETWORKING" name="Networking" title="Networking and Partnerships" delete="true">
        <If id="is_pl" if="{contains({$my_full_roles},PL)}">
            <!-- Project Leader View -->
            <Static>
                <![CDATA[
                    {set(collaborations,)}
                    {set(resources,)}
                    {set(accomplishment,)}
                ]]>
            </Static>
            <ReportItemSet id="people" type="ProjectPeopleNoLeadersReportItemSet" roles="NI,NFI,CI,AR,OldNI,FAKENI">
                <Static>
                    <![CDATA[
                        {set(collaborations,{concat({get(collaborations)}, 
                            {concat(<h3>{$user_name}</h3>,
                                {getText(RP_PROGRESS,NETWORKING,COLLABORATIONS,{$user_id},0,{$project_id})}
                            )}
                        )})}
                        
                        {set(resources,{concat({get(resources)}, 
                            {concat(<h3>{$user_name}</h3>,
                                {getText(RP_PROGRESS,NETWORKING,RESOURCES,{$user_id},0,{$project_id})}
                            )}
                        )})}
                        
                        {set(accomplishment,{concat({get(accomplishment)}, 
                            {concat(<h3>{$user_name}</h3>,
                                {getText(RP_PROGRESS,NETWORKING,ACCOMPLISHMENT,{$user_id},0,{$project_id})}
                            )}
                        )})}
                    ]]>
                </Static>
            </ReportItemSet>
            <ReportItem id="collaborations_popup" type="PopupReportItem" title="NI Comments" text="{get(collaborations)}">
                <![CDATA[
                    <p><b>Describe all collaborations and partners related to the project</b></p>
                    {$item}
                ]]>
            </ReportItem>
            <ReportItem id="collaborations" type="TextareaReportItem" blobItem="COLLABORATIONS">
                <![CDATA[
                    {$item}
                ]]>
            </ReportItem>
            <ReportItem id="resources_popup" type="PopupReportItem" title="NI Comments" text="{get(resources)}">
                <![CDATA[
                    <p><b>Describe how resources and facilities have been optimised through collaborations.</b></p>
                    {$item}
                ]]>
            </ReportItem>
            <ReportItem id="resources" type="TextareaReportItem" blobItem="RESOURCES">
                <![CDATA[
                    {$item}
                ]]>
            </ReportItem>
        </If>
        <If id="not_pl" if="{and({or({contains({$my_full_roles},CI)},{contains({$my_full_roles},AR)},{contains({$my_full_roles},FAKENI)})},{!contains({$my_full_roles},PL)})}">
            <!-- Network Investigator View -->
            <ReportItem id="collaborations" type="TextareaReportItem" blobItem="COLLABORATIONS" blobSubItem="{$my_id}">
                <![CDATA[
                    <p><b>Describe all collaborations and partners related to the project</b></p>
                    {$item}
                ]]>
            </ReportItem>
            <ReportItem id="resources" type="TextareaReportItem" blobItem="RESOURCES" blobSubItem="{$my_id}">
                <![CDATA[
                    <p><b>Describe how resources and facilities have been optimised through collaborations.</b></p>
                    {$item}
                ]]>
            </ReportItem>
        </If>
    </ReportSection>
    <ReportSection id="hqp" type="EditableReportSection" blobSection="HQP" name="HQP" title="Development of Highly Qualified Personnel">
        <If id="is_pl" if="{contains({$my_full_roles},PL)}">
            <!-- Project Leader View -->
            <Static>
                <![CDATA[
                    <div class='info'>HQP responses may be edited by the Project Leader, Network Investigators, and by the HQP themselves.</div>
                ]]>
            </Static>
            <Static>
                <![CDATA[
                    <p>Below are the HQP which are in {$project_name}.  If no HQP are listed, or some are missing then you can add them to the project by going to <a href='https://forum.glyconet.ca/index.php/Special:ManagePeople' target='_blank'>Manage People</a></p>
                ]]>
            </Static>
            <ReportItemSet id="hqps" type="ProjectAllPeopleReportItemSet" startDate="{$this_year}-04-01 00:00:00" endDate="{$next_year}-04-30 00:00:00" role="HQP">
                <ReportItemSet id="header" type="ToggleHeaderReportItemSet" title="{$user_name}">
                    <ReportItem id="roles" type="TextareaReportItem" blobItem="ROLES" blobSubItem="{$user_id}" rich="true" limit="200" recommended="true">
                        <![CDATA[
                            <p><b>Describe the role of the trainee within the project, highlighting progress made to date.</b></p>
                            {$item}
                        ]]>
                    </ReportItem>
                    <ReportItem id="training" type="TextareaReportItem" blobItem="TRAINING" blobSubItem="{$user_id}">
                        <![CDATA[
                            <p><b>Describe any training initiatives undertaken during the funding period</b></p>
                            {$item}
                        ]]>
                    </ReportItem>
                    <ReportItem id="graduate" type="TextareaReportItem" blobItem="GRADUATE" blobSubItem="{$user_id}">
                        <![CDATA[
                            <p><b>If the trainee graduated or transitioned to the workforce, describe his/her new position and location. If a thesis was produced, please give its title.</b></p>
                            {$item}
                        ]]>
                    </ReportItem>
                </ReportItemSet>
            </ReportItemSet>
        </If>
        <If id="not_pl" if="{and({or({contains({$my_full_roles},CI)},{contains({$my_full_roles},AR)},{contains({$my_full_roles},FAKENI)})},{!contains({$my_full_roles},PL)})}">
            <!-- Network Investigator View -->
            <Static>
                <![CDATA[
                    <p>Below are the HQP which you supervise in {$project_name}.  If no HQP are listed, or some are missing then you can add them by going to <a href='https://forum.glyconet.ca/index.php/Special:ManagePeople' target='_blank'>Manage People</a></p>
                ]]>
            </Static>
            <ReportItemSet id="hqps" type="PersonSupervisesReportItemSet" startDate="{$this_year}-04-01 00:00:00" endDate="{$next_year}-04-30 00:00:00" project="{$project_name}" personId="{$my_id}">
                <ReportItemSet id="header" type="ToggleHeaderReportItemSet" title="{$user_name}">
                    <ReportItem id="roles" type="TextareaReportItem" blobItem="ROLES" blobSubItem="{$user_id}" rich="true" limit="200" recommended="true">
                        <![CDATA[
                            <p><b>Describe the role of the trainee within the project, highlighting progress made to date.</b></p>
                            {$item}
                        ]]>
                    </ReportItem>
                    <ReportItem id="training" type="TextareaReportItem" blobItem="TRAINING" blobSubItem="{$user_id}">
                        <![CDATA[
                            <p><b>Describe any training or professional development experiences undertaken during the funding period.</b></p>
                            {$item}
                        ]]>
                    </ReportItem>
                    <ReportItem id="graduate" type="TextareaReportItem" blobItem="GRADUATE" blobSubItem="{$user_id}">
                        <![CDATA[
                            <p><b>Did the trainee graduate or transition to the workforce? Describe.</b> <a href='{$user_url}?tab=hqp-alumni' target='_blank'>Update HQP Alumni</a></p>
                            {$item}
                        ]]>
                    </ReportItem>
                </ReportItemSet>
            </ReportItemSet>
        </If>
        <If id="not_pl" if="{and({contains({$my_full_roles},HQP)},{!contains({$my_full_roles},PL)})}">
            <!-- HQP View -->
            <ReportItem id="roles" type="TextareaReportItem" blobItem="ROLES" blobSubItem="{$my_id}">
                <![CDATA[
                    <div class='info'>Your responses may be edited by the Project Leader, and by the Network Investigators</div>
                    <p><b>Describe your role as a trainee within the project</b></p>
                    {$item}
                ]]>
            </ReportItem>
            <ReportItem id="training" type="TextareaReportItem" blobItem="TRAINING" blobSubItem="{$my_id}">
                <![CDATA[
                    <p><b>Describe any training or professional development experiences undertaken during the funding period.</b></p>
                    {$item}
                ]]>
            </ReportItem>
            <ReportItem id="graduate" type="TextareaReportItem" blobItem="GRADUATE" blobSubItem="{$my_id}">
                <![CDATA[
                    <p><b>Did you graduate or transition to the workforce? Describe.</b></p>
                    {$item}
                ]]>
            </ReportItem>
        </If>
    </ReportSection>
    <ReportSection id="budget" type="EditableReportSection" blobSection="BUDGET" name="Budget" title="Budget Justification">
        <Static>
            <![CDATA[
                <p><b>Provide a written justification for any significant (>20%) deviation of any line item from the original budget in your approved proposal.</b></p>
                <p>In addition, please ensure the HQP Contribution table provides the names, position, and salary details for all HQP working on this project.</p>
            ]]>
        </Static>
        <If id="is_pl" if="{contains({$my_full_roles},PL)}">
            <Static>
                <![CDATA[
                    {set(just,)}
                ]]>
            </Static>
            <ReportItemSet id="people" type="ProjectPeopleNoLeadersReportItemSet" roles="NI,NFI,CI,AR,OldNI,FAKENI">
                <Static>
                    <![CDATA[
                        {set(just,{concat({get(just)}, 
                            {concat(<h3>{$user_name}</h3>,
                                {getText(RP_PROGRESS,BUDGET,JUSTIFICATION,{$user_id},0,{$project_id})}
                            )}
                        )})}
                    ]]>
                </Static>
            </ReportItemSet>
            <ReportItem id="impact_popup" type="PopupReportItem" title="NI Comments" text="{get(just)}">
                <![CDATA[
                    {$item}
                ]]>
            </ReportItem>
        </If>
        <ReportItem id="justification" type="TextareaReportItem" blobItem="JUSTIFICATION" blobSubItem="{$my_id}">
            <![CDATA[
                {$item}
            ]]>
        </ReportItem>
        <Static>
            <![CDATA[
                <h3>HQP Contribution Table</h3>
                <table class='wikitable hqp-budget'>
                    <tr>
                        <th rowspan='2'>Name</th>
                        <th rowspan='2'>Title</th>
                        <th rowspan='2'># Months<br />working on<br />GlycoNet Project<br />(1-12)</th>
                        <th colspan='5'>%Salary/time<br />devoted to project*</th>
                        <th colspan='2'>Person Years</th>
                    </tr>
                    <tr>
                        <th>Paid from<br />NCE funds</th>
                        <th>Paid from<br />other funds</th>
                        <th>Source of<br />non-NCE Funds</th>
                        <th>Category of<br />non-NCE Funds</th>
                        <th>$ Value of<br />non-NCE Funds</th>
                        <th>Paid from<br />NCE funds</th>
                        <th>Paid from<br />other funds</th>
                    </tr>
                    <tbody>
            ]]>
        </Static>
        <ReportItemSet id="hqps" type="ProjectAllPeopleReportItemSet" role="HQP" startDate="{$this_year}-04-01 00:00:00" endDate="{$next_year}-04-30 00:00:00">
            <Static>
                <![CDATA[
                    <tr>
                        <td>{$user_name}</td>
                        <td align='center'>{$user_level}</td>
                ]]>
            </Static>
            <ReportItem id="hqp_months" type="IntegerReportItem" blobItem="HQP_MONTHS" blobSubItem="{$user_id}" max="100" min="1" size="4">
                <![CDATA[
                        <td align='center' class='months'>{$item}</td>
                ]]>
            </ReportItem>
            <ReportItem id="hqp_nce" type="IntegerReportItem" blobItem="HQP_NCE" blobSubItem="{$user_id}" max="100" min="0" size="4">
                <![CDATA[
                        <td align='center' class='nce'>{$item}</td>
                ]]>
            </ReportItem>
            <ReportItem id="hqp_other" type="IntegerReportItem" blobItem="HQP_OTHER" blobSubItem="{$user_id}" max="100" min="0" size="4">
                <![CDATA[
                        <td align='center' class='other'>{$item}</td>
                ]]>
            </ReportItem>
            <ReportItem id="hqp_source" type="TextReportItem" blobItem="HQP_SOURCE" blobSubItem="{$user_id}">
                <![CDATA[
                        <td align='center' class='other'>{$item}</td>
                ]]>
            </ReportItem>
            <ReportItem id="hqp_category" type="SelectReportItem" blobItem="HQP_CATEGORY" blobSubItem="{$user_id}" options="Federal|Provincial|Industry|Foundation|University|International|Other">
                <![CDATA[
                        <td align='center' class='other'>{$item}</td>
                ]]>
            </ReportItem>
            <ReportItem id="hqp_value" type="IntegerReportItem" blobItem="HQP_VALUE" blobSubItem="{$user_id}" size="6">
                <![CDATA[
                        <td align='center' class='other'>{$item}</td>
                ]]>
            </ReportItem>
            <Static>
                <![CDATA[
                        <td align='center' class='calc_nce'></td>
                        <td align='center' class='calc_other'></td>
                    </tr>
                ]]>
            </Static>
        </ReportItemSet>
        <Static>
            <![CDATA[
                    </tbody>
                </table>
                <p>*For example, if a technician was devoting half of his/her salaried time to a GlycoNet project, and that time was paid for equally by NCE and external funds, then the "Paid from NCE funds" and "Paid from other funds" columns would each be 25%.</p>
                <script type="text/javascript">
                    var calcs = function(){
                        var rows = $(".hqp-budget tbody tr");
                        rows.each(function(i, el){
                            var months = parseInt($(".months input", el).val());
                            var nce = parseInt($(".nce input", el).val());
                            var other = parseInt($(".other input", el).val());
                            var nce_time = ((nce/12)/100*months);
                            var other_time = ((other/12)/100*months);
                            
                            if(_.isNaN(nce_time)){ nce_time = ""; }
                            if(_.isNaN(other_time)){ other_time = ""; }
                            
                            $(".calc_nce", el).html(nce_time.toLocaleString("en-CA", {minimumSignificantDigits: 3, maximumSignificantDigits: 3}));
                            $(".calc_other", el).html(other_time.toLocaleString("en-CA", {minimumSignificantDigits: 3, maximumSignificantDigits: 3}));
                        }); 
                    };
                    
                    $(".hqp-budget input").change(calcs);
                    $(".hqp-budget input").keyup(calcs);
                    calcs();
                </script>
            ]]>
        </Static>
    </ReportSection>
    <ReportSection id="contributions" type="EditableReportSection" blobSection="CONTRIBUTIONS" name="Partner Contributions" title="Partner Contributions" delete="true">
        <ReportItem id="cash_contributions" type="MultiText" blobType="BLOB_ARRAY" blobItem="CASH" labels="Source of Funds|Amount &lt;u>Received within the fiscal year&lt;/u>|Use of funds|Notes/Comments|Balance of unused funds|University receiving funds" types="Text|Integer|Select(Bachelors - Canadian and Permanent Residents,Bachelors - Foreign,Masters - Canadian and Permanent Residents,Masters - Foreign,Doctorate - Canadian and Permanent Residents,Doctorate - Foreign,Post-doctoral - Canadian and Permanent Residents,Post-doctoral - Foreign,Equipment,Materials\, supplies and other expenditures,Travel,Other (Please describe))|Textarea|Integer|Text" sizes="|75|250||75|175" multiple="true" addText="Add Contribution">
            <![CDATA[
                Contact information for each funding source described in the tables below should be entered into the "Partners and Collaborators" table in the Project Information tab.
                <h3>Cash Contributions</h3>
                {$item}
                <small>*Add additional lines for different uses of funds from the same source</small>
            ]]>
        </ReportItem>
        <ReportItem id="inkind_contributions" type="MultiText" blobType="BLOB_ARRAY" blobItem="INKIND" labels="Source of Funds|Amount &lt;u>Received within the fiscal year&lt;/u>|Use of Funds|Description|University receiving contribution" types="Text|Integer|Select(Equipment\, software,Materials,Logistical support of field work,Provision of services,Use of company facilities,Salaries of scientific staff,Salaries of managerial\, administrative staff,Project-related travel,Other (specify))|Textarea|Text" sizes="|75|250||175" multiple="true" addText="Add Contribution">
            <![CDATA[
                <h3>In-Kind Contributions</h3>
                {$item}
                <small>*Add additional lines for different uses of funds from the same source</small>
                <p>**Note: In addition to appearing in the tables above, <b>a Statement of Accounts for each non-NCE <u>cash</u> contribution should be emailed to Cécile McNeil (<a href='mailto:ccile@ualberta.ca'>ccile@ualberta.ca</a>)</b>. This document will be prepared by the financial admin office at each institution and will be sent to investigators for review.**</p>
            ]]>
        </ReportItem>
        <ReportItem id="eligible" type="Popup" title="What are eligible contributions?" text="
            &lt;b&gt;Partner contributions may include:&lt;/b&gt;
            &lt;ol type=a&gt;
                &lt;li&gt;Cash contributions&lt;/li&gt;
                &lt;li&gt;In-kind contributions
                    &lt;ul&gt;
                        &lt;li&gt;Equipment &amp; software&lt;/li&gt;
                        &lt;li&gt;Materials&lt;/li&gt;
                        &lt;li&gt;Logistical support of fieldwork&lt;/li&gt;
                        &lt;li&gt;Provision of services&lt;/li&gt;
                        &lt;li&gt;Use of company facilities&lt;/li&gt;
                        &lt;li&gt;Salaries of scientific staff&lt;/li&gt;
                        &lt;li&gt;Salaries of managerial and administrative staff&lt;/li&gt;
                        &lt;li&gt;Project related travel&lt;/li&gt;
                        &lt;li&gt;Other&lt;/li&gt;
                    &lt;/ul&gt;
                &lt;/li&gt;
            &lt;/ol&gt;
            &lt;b&gt;Do not include:&lt;/b&gt;
            &lt;ul&gt;
                &lt;li&gt;grants from federal granting agencies, such as NSERC, CIHR, SSHRC, CFI or Genome Canada and its provincial centres for research, equipment, etc.;&lt;/li&gt;
                &lt;li&gt;contributions from partners who are funded by federal granting agencies, such as NCE, NSERC, CIHR, SSHRC, CFI or Genome Canada.&lt;/li&gt;
                &lt;li&gt;salaries of individuals who are eligible to receive funds directly from the granting agencies (e.g. faculty members of postsecondary institutions) and any associated administrative overhead costs.&lt;/li&gt;
                &lt;li&gt;contributions or contracts outside of the scope of the network’s activities.&lt;/li&gt;
                &lt;li&gt;time on committees and boards.&lt;/li&gt;
            &lt;/ul&gt;">
            <![CDATA[
                {$item}<br />
            ]]>
        </ReportItem>
        <ReportItem id="justification" type="TextareaReportItem" blobItem="JUSTIFICATION">
            <![CDATA[
                <h3>Explanation</h3>
                <p><b>Provide a written explanation of any deviation between the actual contributions and anticipated expenditures and those proposed in the original approved proposal.</b></p>
                {$item}
            ]]>
        </ReportItem>
        <ReportItem id="potentials" type="MultiText" blobItem="POTENTIALS" blobType="BLOB_ARRAY" labels="Partner Organization|Top-Most Executive Contact|Potential Role in GlycoNet's Legacy" multiple="true">
            <![CDATA[
                <h3>Potential GlycoNet Partners for Legacy</h3>
                <p>GlycoNet management is compiling a list of potential partners who may be interested in working with the network after Cycle II. Potential partnerships could be at the network level or with individual projects, and could involve industry, government, foundations, etc. Please fill in the following table with any contacts that you may have.</p>
                {$item}
            ]]>
        </ReportItem>
    </ReportSection>
    <ReportSection id="ccv" type="EditableReportSection" blobSection="CCV" name="CCV" title="CCV" delete="true">
        <ReportItem id="ccv" type="UploadReportItem" blobItem="CCV" blobSubItem="{$my_id}" fileSize="5" mimeType="application/pdf">
            <![CDATA[
                <p><b>CCV Upload (PDF)</b></p>
                {$item}
            ]]>
        </ReportItem>
        <If id="is_pl" if="{contains({$my_full_roles},PL)}">
            <!-- Project Leader View -->
            <ReportItemSet id="people" type="ProjectPeopleNoLeadersReportItemSet" roles="NI,NFI,CI,AR,OldNI,FAKENI">
                <If id="if_null" if="{!=({getBlobMD5(RP_PROGRESS,CCV,CCV,{$user_id},0,{$project_id})},)}">
                    <![CDATA[
                        <p><b>{$user_name}</b><br />
                        <a href='{$wgServer}{$wgScriptPath}/index.php?action=downloadBlob&id={getBlobMD5(RP_PROGRESS,CCV,CCV,{$user_id},0,{$project_id})}&mime=application/pdf'>Download CCV</a></p>
                    ]]>
                </If>
            </ReportItemSet>
        </If>
    </ReportSection>
    <ReportSection id="extension" type="EditableReportSection" blobSection="EXTENSION" name="Request for Extension" title="Request for Extension - 2017/2018 Collaborative Team Grants" delete="true">
        <ReportItem id="check" type="Radio" blobType="BLOB_TEXT" blobItem="CHECK" options="a) Collaborative Team Grant|b) Translational Grant|c) Either a Collaborative Team Grant or a Translational Grant|d) We do not wish to extend this project">
            <![CDATA[
                <p>Round 3 and 4 Collaborative Team Grants (e.g. projects ending June 2019 or December 2019) may apply for a project extension to March 31, 2020 by completing this section.</p>
                <!--p>Please indicate which grant stream you would like this project extension request to be considered for:</p>
                {$item}-->
            ]]>
        </ReportItem>
        <ReportItem id="extension" type="TextareaReportItem" blobItem="OBJECTIVES" rich="true" limit="2000" recommended="true" optional="true">
            <![CDATA[
                <h2>Objectives during the renewal period and justification based on progress to date</h2>
                {$item}
            ]]>
        </ReportItem>
        <ReportItem id="figures" type="UploadReportItem" blobItem="FIGURES" fileSize="20" mimeType="application/pdf" optional="true">
            <![CDATA[
                <h3>Figures & Schemes PDF upload</h3>
                {$item}
            ]]>
        </ReportItem>
        <ReportItem id="milestones" type="UploadReportItem" blobType="BLOB_EXCEL" blobItem="MILESTONES" mimeType="application/vnd.openxmlformats-officedocument.spreadsheetml.sheet,application/vnd.ms-excel" optional="true">
            <![CDATA[
                <h2>Milestones <small>(from time of renewal to March 31, 2020)</small></h2>
                <p>
                    Please download the following <a href="{$wgServer}{$wgScriptPath}/data/GlycoNet%20Milestones.xls">milestone template</a> and upload it below.
                </p>
                {$item}
            ]]>
        </ReportItem>
        <ReportItem id="budget" type="UploadReportItem" blobType="BLOB_EXCEL" blobItem="BUDGET" mimeType="application/vnd.openxmlformats-officedocument.spreadsheetml.sheet,application/vnd.ms-excel" optional="true">
            <![CDATA[
                <h2>Budget <small>(from time of renewal to March 31, 2020)</small></h2>
                <p>
                    Please download the following <a href="{$wgServer}{$wgScriptPath}/data/GlycoNet Budget Template.xlsx">budget template</a> and upload it below.
                </p>
                {$item}
            ]]>
        </ReportItem>
        <ReportItem id="justification" type="TextareaReportItem" blobItem="JUSTIFICATION" rich="true">
            <![CDATA[
                <h3>Budget Justification</h3>
                {$item}
            ]]>
        </ReportItem>
        <ReportItem id="contributions" type="MultiTextReportItem" blobType="BLOB_ARRAY" blobItem="CONTRIBUTIONS" labels="Contribution Amount ($CAD)|Cash/In-kind|Partner Organization|Contact Name|Contact Email/Phone" types="Integer|Select(Cash,In-kind,Both)|String|String|String" sizes="100||||" multiple="true" optional="true">
            <![CDATA[
                <h2>Expected matching</h2>
                <p>Projects are expected to leverage at minimum a 2:1 matching funds (i.e., for every $2 in GlycoNet funding, $1 in matching is expected; at least 50% of the total matching contribution must be cash.).</p>
                {$item}
            ]]>
        </ReportItem>
        <ReportItem id="letters" type="UploadReportItem" blobType="BLOB_RAW" blobItem="LETTERS" mimeType="application/zip,.zip" fileSize="20" optional="true">
            <![CDATA[
                <h3>Letter of Support (if available)*</h3>
                <p>Upload a single <b><a target='_blank' href='http://www.wikihow.com/Make-a-Zip-File'>single ZIP file</a></b> containing all letters of support.</p>
                {$item}
                <small>*Letters of support are not required for the extension request, but should be in place before funding is released</small>
            ]]>
        </ReportItem>
        <!--Static>
            <![CDATA[
                <h2>IP development strategy/commercialization plan</h2>
                <p>If you wish to be considered for a Translational Grant (options b or c, above), please email a commercialization plan to Elizabeth Nanak (<a href='mailto:enanak@ualberta.ca'>enanak@ualberta.ca</a>) no later than June 1, 2019.</p>
                <ul>
                    <li>Provided by the Technology Transfer Office of the Project Leader’s Institution;</li>
                    <li>Five pages maximum (2 cm (0.75 inch) margins, 12 point Times New Roman font (regular, not condensed) and a minimum of six lines per inch;</li>
                    <li>The plan should address the following items:
                        <ul>
                            <li>Intellectual Property and Relevant Patents, or Patentability Strategy</li>
                            <li>Market</li>
                            <li>Barriers</li>
                            <li>Commercialization Opportunity</li>
                            <li>Competitive Advantage over other Technologies</li>
                            <li>Business Expertise</li>
                            <li>Commercialization Strategy</li>
                            <li>Timelines</li>
                        </ul>
                    </li>
                </ul>
            ]]>
        </Static-->
    </ReportSection>
    <ReportSection id="review" tooltip="Review of on-line report content" name="Review" blobSection="SEC_NONE" type="ReportSection" renderpdf="false">
        <ReportItem id="report_review" type="ReviewReportItem">
            <![CDATA[{$item}]]>
        </ReportItem>
    </ReportSection>
    <ReportSection id="submit" tooltip="PDF generation of the Review" name="Submit" blobSection="SEC_NONE" type="ReportSection" renderpdf="false">
        <Static>
            <![CDATA[
                <div id='reportWarnings'></div>
                <table class='wikitable hqps' style='display:none;'>
            ]]>
        </Static>
        <ReportItemSet id="hqps" type="ProjectAllPeopleReportItemSet" role="HQP" startDate="{$this_year}-04-01 00:00:00" endDate="{$next_year}-04-30 00:00:00">
            <Static>
                <![CDATA[
                    <tr>
                        <td>{$user_name}</td>
                        <td>{$user_uni}</td>
                        <td>{$user_level}</td>
                        <td>{$user_email}</td>
                        <td>{$user_supervisors}</td>
                    </tr>
                ]]>
            </Static>
        </ReportItemSet>
        <Static>
            <![CDATA[
                </table>
                <script type="text/javascript">
                    if($("table.hqps td").is(':empty')){
                        addWarning('The <b>Project Information &gt; Trainees and role</b> table is not complete.', false, "#reportWarnings");
                    }
                </script>
            ]]>
        </Static>
        <ReportItem id="review" type="SimpleReviewSubmitReportItem" emails="{$my_email},info@glyconet.ca,enanak@ualberta.ca,vsharko@glyconet.ca" text="" />
        <Static>
            <![CDATA[
                <br />
                <br />
            ]]>
        </Static>
    </ReportSection>
</Report>
